{
  "kind": "collectionType",
  "collectionName": "form_donatepapers",
  "info": {
    "singularName": "form-donatepaper",
    "pluralName": "form-donatepapers",
    "displayName": "form-donatepaper",
    "description": ""
  },
  "options": {
    "draftAndPublish": false
  },
  "pluginOptions": {},
  "attributes": {
    "name": {
      "type": "string"
    },
    "role_at_nwc": {
      "type": "string"
    },
    "address": {
      "type": "text"
    },
    "phone": {
      "type": "string"
    },
    "email": {
      "type": "email"
    },
    "comments": {
      "type": "text"
    }
  }
}
